{
  "firstNames": [
    {
      "name": "Aaron",
      "gender": "Male"
    },
    {
      "name": "Abraham",
      "gender": "Male"
    },
    {
      "name": "Aidan",
      "gender": "Male"
    },
    {
      "name": "Alan",
      "gender": "Male"
    },
    {
      "name": "Alexander",
      "gender": "Male"
    },
    {
      "name": "Alton",
      "gender": "Male"
    },
    {
      "name": "Andrew",
      "gender": "Male"
    },
    {
      "name": "Anthony",
      "gender": "Male"
    },
    {
      "name": "Arlo",
      "gender": "Male"
    },
    {
      "name": "Armstrong",
      "gender": "Male"
    },
    {
      "name": "Arthur",
      "gender": "Male"
    },
    {
      "name": "Benedict",
      "gender": "Male"
    },
    {
      "name": "Benjamin",
      "gender": "Male"
    },
    {
      "name": "Bernard",
      "gender": "Male"
    },
    {
      "name": "Bran",
      "gender": "Male"
    },
    {
      "name": "Cameron",
      "gender": "Male"
    },
    {
      "name": "Caspian",
      "gender": "Male"
    },
    {
      "name": "Charles",
      "gender": "Male"
    },
    {
      "name": "Chester",
      "gender": "Male"
    },
    {
      "name": "Christopher",
      "gender": "Male"
    },
    {
      "name": "Clarence",
      "gender": "Male"
    },
    {
      "name": "Clifton",
      "gender": "Male"
    },
    {
      "name": "Constantine",
      "gender": "Male"
    },
    {
      "name": "Cromwell",
      "gender": "Male"
    },
    {
      "name": "Daniel",
      "gender": "Male"
    },
    {
      "name": "Darian",
      "gender": "Male"
    },
    {
      "name": "David",
      "gender": "Male"
    },
    {
      "name": "Dex",
      "gender": "Male"
    },
    {
      "name": "Edmund",
      "gender": "Male"
    },
    {
      "name": "Edward",
      "gender": "Male"
    },
    {
      "name": "Eldridge",
      "gender": "Male"
    },
    {
      "name": "Ellington",
      "gender": "Male"
    },
    {
      "name": "Ellis",
      "gender": "Male"
    },
    {
      "name": "Elton",
      "gender": "Male"
    },
    {
      "name": "Emerson",
      "gender": "Male"
    },
    {
      "name": "Everest",
      "gender": "Male"
    },
    {
      "name": "Fairfax",
      "gender": "Male"
    },
    {
      "name": "Fenton",
      "gender": "Male"
    },
    {
      "name": "Finn",
      "gender": "Male"
    },
    {
      "name": "Francis",
      "gender": "Male"
    },
    {
      "name": "Frank",
      "gender": "Male"
    },
    {
      "name": "Fred",
      "gender": "Male"
    },
    {
      "name": "Gabriel",
      "gender": "Male"
    },
    {
      "name": "Geoffrey",
      "gender": "Male"
    },
    {
      "name": "George",
      "gender": "Male"
    },
    {
      "name": "Gregory",
      "gender": "Male"
    },
    {
      "name": "Griffith",
      "gender": "Male"
    },
    {
      "name": "Harlow",
      "gender": "Male"
    },
    {
      "name": "Harold",
      "gender": "Male"
    },
    {
      "name": "Harry",
      "gender": "Male"
    },
    {
      "name": "Hawthorne",
      "gender": "Male"
    },
    {
      "name": "Henry",
      "gender": "Male"
    },
    {
      "name": "Hugh",
      "gender": "Male"
    },
    {
      "name": "Humphrey",
      "gender": "Male"
    },
    {
      "name": "Huxley",
      "gender": "Male"
    },
    {
      "name": "Isaac",
      "gender": "Male"
    },
    {
      "name": "James",
      "gender": "Male"
    },
    {
      "name": "Jansen",
      "gender": "Male"
    },
    {
      "name": "Jerome",
      "gender": "Male"
    },
    {
      "name": "Johnathan",
      "gender": "Male"
    },
    {
      "name": "Jonas",
      "gender": "Male"
    },
    {
      "name": "Joseph",
      "gender": "Male"
    },
    {
      "name": "Keith",
      "gender": "Male"
    },
    {
      "name": "Lambert",
      "gender": "Male"
    },
    {
      "name": "Lawrence",
      "gender": "Male"
    },
    {
      "name": "Leonard",
      "gender": "Male"
    },
    {
      "name": "Liam",
      "gender": "Male"
    },
    {
      "name": "Luke",
      "gender": "Male"
    },
    {
      "name": "Malcolm",
      "gender": "Male"
    },
    {
      "name": "Mark",
      "gender": "Male"
    },
    {
      "name": "Martin",
      "gender": "Male"
    },
    {
      "name": "Matthew",
      "gender": "Male"
    },
    {
      "name": "Michael",
      "gender": "Male"
    },
    {
      "name": "Miles",
      "gender": "Male"
    },
    {
      "name": "Morgan",
      "gender": "Male"
    },
    {
      "name": "Morten",
      "gender": "Male"
    },
    {
      "name": "Nathaniel",
      "gender": "Male"
    },
    {
      "name": "Nicholas",
      "gender": "Male"
    },
    {
      "name": "Noah",
      "gender": "Male"
    },
    {
      "name": "Oswald",
      "gender": "Male"
    },
    {
      "name": "Paul",
      "gender": "Male"
    },
    {
      "name": "Penn",
      "gender": "Male"
    },
    {
      "name": "Peter",
      "gender": "Male"
    },
    {
      "name": "Philip",
      "gender": "Male"
    },
    {
      "name": "Preston",
      "gender": "Male"
    },
    {
      "name": "Putnam",
      "gender": "Male"
    },
    {
      "name": "Quinn",
      "gender": "Male"
    },
    {
      "name": "Ralph",
      "gender": "Male"
    },
    {
      "name": "Raymond",
      "gender": "Male"
    },
    {
      "name": "Richard",
      "gender": "Male"
    },
    {
      "name": "Robert",
      "gender": "Male"
    },
    {
      "name": "Roger",
      "gender": "Male"
    },
    {
      "name": "Rowland",
      "gender": "Male"
    },
    {
      "name": "Samuel",
      "gender": "Male"
    },
    {
      "name": "Shawn",
      "gender": "Male"
    },
    {
      "name": "Simon",
      "gender": "Male"
    },
    {
      "name": "Stephen",
      "gender": "Male"
    },
    {
      "name": "Thomas",
      "gender": "Male"
    },
    {
      "name": "Walter",
      "gender": "Male"
    },
    {
      "name": "William",
      "gender": "Male"
    },
    {
      "name": "Abigail",
      "gender": "Female"
    },
    {
      "name": "Ada",
      "gender": "Female"
    },
    {
      "name": "Adelina",
      "gender": "Female"
    },
    {
      "name": "Agnes",
      "gender": "Female"
    },
    {
      "name": "Aldith",
      "gender": "Female"
    },
    {
      "name": "Alexis",
      "gender": "Female"
    },
    {
      "name": "Alice",
      "gender": "Female"
    },
    {
      "name": "Alina",
      "gender": "Female"
    },
    {
      "name": "Amanda",
      "gender": "Female"
    },
    {
      "name": "Amicia",
      "gender": "Female"
    },
    {
      "name": "Amiria",
      "gender": "Female"
    },
    {
      "name": "Amy",
      "gender": "Female"
    },
    {
      "name": "Anabel",
      "gender": "Female"
    },
    {
      "name": "Anne",
      "gender": "Female"
    },
    {
      "name": "Annora",
      "gender": "Female"
    },
    {
      "name": "Avelina",
      "gender": "Female"
    },
    {
      "name": "Bailey",
      "gender": "Female"
    },
    {
      "name": "Barbara",
      "gender": "Female"
    },
    {
      "name": "Beatrice",
      "gender": "Female"
    },
    {
      "name": "Bela",
      "gender": "Female"
    },
    {
      "name": "Bridget",
      "gender": "Female"
    },
    {
      "name": "Carolyn",
      "gender": "Female"
    },
    {
      "name": "Catherine",
      "gender": "Female"
    },
    {
      "name": "Cecilia",
      "gender": "Female"
    },
    {
      "name": "Cecily",
      "gender": "Female"
    },
    {
      "name": "Celestria",
      "gender": "Female"
    },
    {
      "name": "Charlotte",
      "gender": "Female"
    },
    {
      "name": "Christiana",
      "gender": "Female"
    },
    {
      "name": "Clarice",
      "gender": "Female"
    },
    {
      "name": "Clemence",
      "gender": "Female"
    },
    {
      "name": "Constance",
      "gender": "Female"
    },
    {
      "name": "Deborah",
      "gender": "Female"
    },
    {
      "name": "Dinah",
      "gender": "Female"
    },
    {
      "name": "Dorothy",
      "gender": "Female"
    },
    {
      "name": "Edith",
      "gender": "Female"
    },
    {
      "name": "Eleanor",
      "gender": "Female"
    },
    {
      "name": "Elinor",
      "gender": "Female"
    },
    {
      "name": "Elizabeth",
      "gender": "Female"
    },
    {
      "name": "Ellen",
      "gender": "Female"
    },
    {
      "name": "Emma",
      "gender": "Female"
    },
    {
      "name": "Esther",
      "gender": "Female"
    },
    {
      "name": "Eva",
      "gender": "Female"
    },
    {
      "name": "Faith",
      "gender": "Female"
    },
    {
      "name": "Felicia",
      "gender": "Female"
    },
    {
      "name": "Felicity",
      "gender": "Female"
    },
    {
      "name": "Florence",
      "gender": "Female"
    },
    {
      "name": "Frances",
      "gender": "Female"
    },
    {
      "name": "Gertrude",
      "gender": "Female"
    },
    {
      "name": "Godiva",
      "gender": "Female"
    },
    {
      "name": "Grace",
      "gender": "Female"
    },
    {
      "name": "Hannah",
      "gender": "Female"
    },
    {
      "name": "Harriet",
      "gender": "Female"
    },
    {
      "name": "Helen",
      "gender": "Female"
    },
    {
      "name": "Hester",
      "gender": "Female"
    },
    {
      "name": "Honour",
      "gender": "Female"
    },
    {
      "name": "Isabel",
      "gender": "Female"
    },
    {
      "name": "Isolde",
      "gender": "Female"
    },
    {
      "name": "Jane",
      "gender": "Female"
    },
    {
      "name": "Janet",
      "gender": "Female"
    },
    {
      "name": "Jemima",
      "gender": "Female"
    },
    {
      "name": "Joan",
      "gender": "Female"
    },
    {
      "name": "Joanna",
      "gender": "Female"
    },
    {
      "name": "Joyce",
      "gender": "Female"
    },
    {
      "name": "Judith",
      "gender": "Female"
    },
    {
      "name": "Juliana",
      "gender": "Female"
    },
    {
      "name": "Katherine",
      "gender": "Female"
    },
    {
      "name": "Kennedy",
      "gender": "Female"
    },
    {
      "name": "Leah",
      "gender": "Female"
    },
    {
      "name": "Lucia",
      "gender": "Female"
    },
    {
      "name": "Lucy",
      "gender": "Female"
    },
    {
      "name": "Mabel",
      "gender": "Female"
    },
    {
      "name": "Margaret",
      "gender": "Female"
    },
    {
      "name": "Margery",
      "gender": "Female"
    },
    {
      "name": "Marjorie",
      "gender": "Female"
    },
    {
      "name": "Marsilia",
      "gender": "Female"
    },
    {
      "name": "Martha",
      "gender": "Female"
    },
    {
      "name": "Mary",
      "gender": "Female"
    },
    {
      "name": "Maud",
      "gender": "Female"
    },
    {
      "name": "Mercy",
      "gender": "Female"
    },
    {
      "name": "Mildred",
      "gender": "Female"
    },
    {
      "name": "Millicent",
      "gender": "Female"
    },
    {
      "name": "Morgan",
      "gender": "Female"
    },
    {
      "name": "Muriel",
      "gender": "Female"
    },
    {
      "name": "Nicola",
      "gender": "Female"
    },
    {
      "name": "Noel",
      "gender": "Female"
    },
    {
      "name": "Patience",
      "gender": "Female"
    },
    {
      "name": "Penelope",
      "gender": "Female"
    },
    {
      "name": "Philippa",
      "gender": "Female"
    },
    {
      "name": "Phyllis",
      "gender": "Female"
    },
    {
      "name": "Prudence",
      "gender": "Female"
    },
    {
      "name": "Rachel",
      "gender": "Female"
    },
    {
      "name": "Rebecca",
      "gender": "Female"
    },
    {
      "name": "Regan",
      "gender": "Female"
    },
    {
      "name": "Rosamund",
      "gender": "Female"
    },
    {
      "name": "Rose",
      "gender": "Female"
    },
    {
      "name": "Sabina",
      "gender": "Female"
    },
    {
      "name": "Sarah",
      "gender": "Female"
    },
    {
      "name": "Susanna",
      "gender": "Female"
    },
    {
      "name": "Sybil",
      "gender": "Female"
    },
    {
      "name": "Temperance",
      "gender": "Female"
    },
    {
      "name": "Theodosia",
      "gender": "Female"
    },
    {
      "name": "Thomasin",
      "gender": "Female"
    },
    {
      "name": "Ursula",
      "gender": "Female"
    },
    {
      "name": "Winifred",
      "gender": "Female"
    }
  ],
  "lastNames": [
    "Abell",
    "Abery",
    "Acworth",
    "Adams",
    "Addicock",
    "Alard",
    "Albyn",
    "Aldebourne",
    "Alfraye",
    "Alikok",
    "Alington",
    "Alleine",
    "Amcottes",
    "Amondesham",
    "Andrews",
    "Annesley",
    "Ansty",
    "Archer",
    "Ardalle",
    "Arderne",
    "Argentein",
    "Arnold",
    "Arthur",
    "Asger",
    "Ashenhurst",
    "Ashtor",
    "Askew",
    "Asplyn",
    "Assheby",
    "Assheton",
    "Astley",
    "Atherton",
    "Atkinson",
    "Atlee",
    "Attilburgh",
    "Aubrey",
    "Audeley",
    "Auldyngton",
    "Aumberden",
    "Ayde",
    "Ayleward",
    "Aylmer",
    "Aynesworth",
    "Ayshecombe",
    "Babham",
    "Babyngton",
    "Bacon",
    "Badby",
    "Bailey",
    "Baker",
    "Balam",
    "Baldwin",
    "Ballard",
    "Ballett",
    "Bamard",
    "Barantyn",
    "Barber",
    "Bardolf",
    "Baret",
    "Barfoot",
    "Barker",
    "Barnes",
    "Barre",
    "Barrentyne",
    "Barstaple",
    "Bartelot",
    "Barton",
    "Basset",
    "Batherst",
    "Battersby",
    "Battyl",
    "Baynton",
    "Beauchamp",
    "Beaumont",
    "Beaurepaire",
    "Bedell",
    "Bedgbery",
    "Bedingfeld",
    "Beel",
    "Beer",
    "Bekyngham",
    "Bell",
    "Bende",
    "Bennet",
    "Benthey",
    "Berdwell",
    "Berecraft",
    "Beresford",
    "Berkhead",
    "Bernard",
    "Bernewelt",
    "Berney",
    "Berry",
    "Berwyk",
    "Best",
    "Beton",
    "Bettesthorne",
    "Bewforest",
    "Bewley",
    "Bexley",
    "Bigley",
    "Bilingford",
    "Bischoptree",
    "Bishop",
    "Bladwell",
    "Blakeley",
    "Blakewell",
    "Blaknall",
    "Blakwall",
    "Blakwell",
    "Blenerhayset",
    "Blexham",
    "Blodwell",
    "Blome",
    "Blondell",
    "Blount",
    "Blundell",
    "Boddinham",
    "Bohan",
    "Boote",
    "Boothe",
    "Borell",
    "Borrow",
    "Bosby",
    "Bost",
    "Bostock",
    "Boston",
    "Boteler",
    "Bothy",
    "Bouldre",
    "Bourne",
    "Boville",
    "Bowcer",
    "Bowett",
    "Bownell",
    "Bowthe",
    "Bowyar",
    "Bradbridge",
    "Bradshawe",
    "Bradstane",
    "Bradston",
    "Bramfield",
    "Brampton",
    "Branche",
    "Branwhait",
    "Brassie",
    "Braunstone",
    "Bray",
    "Brayles",
    "Brecknock",
    "Bredham",
    "Brent",
    "Bret",
    "Brewse",
    "Brewster",
    "Brewys",
    "Bridgeman",
    "Briggs",
    "Brinckhurst",
    "Brocksby",
    "Brodeway",
    "Brodnax",
    "Brokhill",
    "Brome",
    "Brook",
    "Brougham",
    "Broughton",
    "Brouncker",
    "Browet",
    "Brown",
    "Brownflet",
    "Brownyng",
    "Brudenell",
    "Bryan",
    "Bryn",
    "Brystowe",
    "Bulkeley",
    "Bulstrode",
    "Burgess",
    "Burgh",
    "Burghehyll",
    "Burgoyn",
    "Burlton",
    "Burnell",
    "Burton",
    "Buryngton",
    "Bushbury",
    "Bushe",
    "Buslingthorpe",
    "Butler",
    "Byfield",
    "Byllyng",
    "Byngham",
    "Byrde",
    "Byschoppeson",
    "Caley",
    "Callthorp",
    "Campeden",
    "Canon",
    "Canteys",
    "Cantilupe",
    "Carbonall",
    "Cardiff",
    "Carew",
    "Carlyll",
    "Carter",
    "Cary",
    "Caseberde",
    "Cassy",
    "Castell",
    "Castletown",
    "Catesby",
    "Cavell",
    "Caxaton",
    "Cely",
    "Chamburleyn",
    "Champneys",
    "Chanceler",
    "Chancey",
    "Chapman",
    "Charlis",
    "Chase",
    "Chatwyn",
    "Chauncey",
    "Chaundeler",
    "Cheberell",
    "Chechester",
    "Cheddar",
    "Chelde",
    "Chelseye",
    "Chernocke",
    "Chester",
    "Chetwoode",
    "Cheyne",
    "Child",
    "Chowne",
    "Chudderle",
    "Churmound",
    "Chylton",
    "Chyrche",
    "Claimond",
    "Clarell",
    "Clark",
    "Clavell",
    "Claybrook",
    "Cleffort",
    "Clement",
    "Clerk",
    "Clifton",
    "Clitherow",
    "Clopton",
    "Clyfford",
    "Cobbe",
    "Cobham",
    "Coblegh",
    "Cockayne",
    "Cod",
    "Codington",
    "Coffyn",
    "Coggeshall",
    "Colard",
    "Colby",
    "Cole",
    "Colkins",
    "Colmer",
    "Colt",
    "Complyn",
    "Compton",
    "Conquest",
    "Cooke",
    "Coorthopp",
    "Copinger",
    "Corbett",
    "Corby",
    "Cossale",
    "Cosworth",
    "Cosyngton",
    "Cotton",
    "Coulthurst",
    "Courtenay",
    "Covert",
    "Cowill",
    "Cox",
    "Crane",
    "Cranford",
    "Crawley",
    "Crekett",
    "Cressy",
    "Crispe",
    "Cristemas",
    "Crocker",
    "Crugge",
    "Cryppys",
    "Cuddon",
    "Culpeper",
    "Cunnyngham",
    "Curson",
    "Curteys",
    "Daelyngridge",
    "Dagworth",
    "Dale",
    "Dalison",
    "Damsell",
    "Danet",
    "Danvers",
    "Darcy",
    "Darley",
    "Daubernoun",
    "Daunce",
    "Daundelyon",
    "Dauntesay",
    "Davers",
    "Davy",
    "Dawne",
    "Day",
    "Deacons",
    "Delabere",
    "Delamere",
    "Dely",
    "Demoke",
    "Dencourt",
    "Dene",
    "Denton",
    "Denys",
    "Dericote",
    "Dering",
    "Deryngton",
    "Desford",
    "Digby",
    "Dixton",
    "Doddle",
    "Dogmersfield",
    "Donnet",
    "Doreward",
    "Dormer",
    "Dove",
    "Dow",
    "Downer",
    "Draper",
    "Draw",
    "Drayton",
    "Driland",
    "Dryden",
    "Dunch",
    "Duncombe",
    "Dunham",
    "Duredent",
    "Dusteby",
    "Dye",
    "Dygenys",
    "Dyneley",
    "Dynham",
    "Echyngham",
    "Edgar",
    "Edgcomb",
    "Edgerley",
    "Edwards",
    "Egerton",
    "Eggerley",
    "Eglisfelde",
    "Eldysley",
    "Elmebrigge",
    "Elyot",
    "Elys",
    "Emerson",
    "Engeham",
    "Engleford",
    "Englysche",
    "Epworth",
    "Erewaker",
    "Ermyn",
    "Ertham",
    "Esmund",
    "Estbury",
    "Estney",
    "Estone",
    "Etton",
    "Everard",
    "Everdon",
    "Evrenden",
    "Evyngar",
    "Eyer",
    "Eyston",
    "Fabyan",
    "Faldo",
    "Fane",
    "Faryndon",
    "Faylare",
    "Fayneman",
    "Felbrigg",
    "Feld",
    "Fenton",
    "Ferrer",
    "Feversham",
    "Ffrewyll",
    "Fienley",
    "Finch",
    "Fitton",
    "Fitzgeffrey",
    "Fitzherbert",
    "Fitzlewis",
    "Fitzralph",
    "Fitzwarym",
    "Fitzwilliyam",
    "Fleet",
    "Fleming",
    "Fletewoode",
    "Flexney",
    "Flower",
    "Fodde",
    "Fogg",
    "Foliot",
    "Foljambe",
    "Follywolle",
    "Folon",
    "Folsham",
    "Forde",
    "Fortescue",
    "Fortey",
    "Fowler",
    "Fox",
    "Francey",
    "Frankeleyn",
    "Fraunces",
    "Freer",
    "Freville",
    "Frilende",
    "Frilleck",
    "Frogenhall",
    "Fromond",
    "Froste",
    "Frowseloure",
    "Frye",
    "Fryth",
    "Fulburne",
    "Fulmer",
    "Funteyn",
    "Furnace",
    "Fynderne",
    "Fyneux",
    "Fysher",
    "Gage",
    "Galey",
    "Garard",
    "Gardyner",
    "Gare",
    "Garneys",
    "Garret",
    "Gascoigne",
    "Gasper",
    "Gavell",
    "Gaynesford",
    "Geddyng",
    "Geffray",
    "George",
    "Gerard",
    "Gerville",
    "Geste",
    "Gibbs",
    "Gifford",
    "Gilbert",
    "Ginter",
    "Glenham",
    "Glennon",
    "Glover",
    "Goberd",
    "Goddam",
    "Godfrey",
    "Golde",
    "Golding",
    "Goldwell",
    "Gomersall",
    "Gomfrey",
    "Gonson",
    "Good",
    "Goodenouth",
    "Goodere",
    "Goodluck",
    "Goodnestone",
    "Goodryke",
    "Goodryngton",
    "Goodwyn",
    "Goring",
    "Gorney",
    "Gorste",
    "Gosebourne",
    "Grafton",
    "Greenway",
    "Grene",
    "Grenefeld",
    "Greville",
    "Grey",
    "Grobbam",
    "Grofhurst",
    "Groston",
    "Grove",
    "Grymbalde",
    "Guildeforde",
    "Gyll",
    "Gysborne",
    "Gyttyns",
    "Hache",
    "Hackeman",
    "Haddock",
    "Haddon",
    "Hadresham",
    "Hakebourne",
    "Hale",
    "Hall",
    "Halley",
    "Halshan",
    "Hambard",
    "Hammer",
    "Hamond",
    "Hampden",
    "Hancock",
    "Hansart",
    "Harbird",
    "Harbotle",
    "Harcourt",
    "Hardy",
    "Harewell",
    "Hargreve",
    "Harlakinden",
    "Harleston",
    "Harley",
    "Harpeden",
    "Harper",
    "Harris",
    "Harryses",
    "Harte",
    "Harwood",
    "Hasard",
    "Hatteclyff",
    "Haukesworth",
    "Hawkins",
    "Hawtrey",
    "Haye",
    "Hayes",
    "Hayton",
    "Helme",
    "Henshawe",
    "Herleston",
    "Heron",
    "Hertcombe",
    "Herwy",
    "Hewes",
    "Heydon",
    "Heywood",
    "Heyworth",
    "Hicchecok",
    "Higate",
    "Higden",
    "Hille",
    "Hoare",
    "Hobart",
    "Hobert",
    "Hodgeson",
    "Holbrook",
    "Holcot",
    "Holes",
    "Holland",
    "Holsey",
    "Holt",
    "Holton",
    "Hopton",
    "Horman",
    "Hornebolt",
    "Hornley",
    "Horsey",
    "Horthall",
    "Horton",
    "Hosteler",
    "Hotham",
    "Howard",
    "Huchenson",
    "Huddleston",
    "Hugeford",
    "Hunden",
    "Hungate",
    "Hunston",
    "Hurst",
    "Hussey",
    "Hyde",
    "Hyenson",
    "Hylderley",
    "Hyll",
    "Inwood",
    "Isley",
    "Jackmann",
    "Jackson",
    "James",
    "Janner",
    "Jarman",
    "Jay",
    "Jendring",
    "Jenney",
    "Johnson",
    "Jordan",
    "Joslyne",
    "Joulon",
    "Jowchet",
    "Kekilpenny",
    "Kellett",
    "Kelly",
    "Kemp",
    "Kent",
    "Keriell",
    "Kesteven",
    "Key",
    "Kidwelly",
    "Killigrew",
    "Kinge",
    "Knevynton",
    "Knighton",
    "Knody",
    "Knoyll",
    "Knyvet",
    "Kottow",
    "Kydwelly",
    "Kyllyngworth",
    "Kyrkeby",
    "Kytson",
    "la Barre",
    "la Hale",
    "la Penne",
    "Lacy",
    "Laken",
    "Lamber",
    "Lambton",
    "Langeton",
    "Langham",
    "Langstone",
    "Lappage",
    "Latham",
    "Latton",
    "Launceleyn",
    "Lave",
    "Lawnder",
    "le Bone",
    "Leeche",
    "Leeds",
    "Lehenard",
    "Leigh",
    "Leighlin",
    "Leman",
    "Lenton",
    "Lestrange",
    "Letterford",
    "Leventhorpe",
    "Leverer",
    "Leveson",
    "Lewys",
    "Leynham",
    "Leynthall",
    "Lichefield",
    "Livesey",
    "Lloyd",
    "Lockton",
    "Lodyngton",
    "Lond",
    "London",
    "Long",
    "Longton",
    "Lovell",
    "Loveney",
    "Loveryk",
    "Lowe",
    "Lowthe",
    "Lucy",
    "Ludsthorp",
    "Luke",
    "Lumbarde",
    "Lupton",
    "Lyfelde",
    "Lymsey",
    "Lynde",
    "Lyon",
    "Lyrypine",
    "Lysle",
    "Lytcott",
    "Lyttleburye",
    "Lytton",
    "Lyveryche",
    "Makepiece",
    "Malemayns",
    "Malster",
    "Maltoun",
    "Malyns",
    "Manfield",
    "Manston",
    "Mapilton",
    "Marcheford",
    "Mareys",
    "Markeley",
    "Marsham",
    "Marten",
    "Mason",
    "Massyngberde",
    "Maudit",
    "Mauntell",
    "Maycot",
    "Maydestone",
    "Mayne",
    "Maynwaring",
    "Mede",
    "Medeley",
    "Merden",
    "Mereworth",
    "Merstun",
    "Merton",
    "Metcalf",
    "Michelgrove",
    "Millys",
    "Milsent",
    "Moland",
    "Molyngton",
    "Molyns",
    "Monde",
    "Montacute",
    "Montagu",
    "Moore",
    "More",
    "Morecote",
    "Morley",
    "Mortymer",
    "Moryet",
    "Morys",
    "Motesfont",
    "Mowfurth",
    "Mugge",
    "Mullens",
    "Muston",
    "Myddilton",
    "Myllet",
    "Mylner",
    "Narbrige",
    "Nash",
    "Neceham",
    "Nele",
    "Nevinson",
    "Newdegate",
    "Newman",
    "Noke",
    "Norbury",
    "Norden",
    "Norrys",
    "North",
    "Northwoode",
    "Norton",
    "Norwich",
    "Norwood",
    "Notfelde",
    "Notyngham",
    "Nysell",
    "Obson",
    "Oke",
    "Oken",
    "Oliver",
    "Olyngworthe",
    "Osborne",
    "Osteler",
    "Osyllbury",
    "Outlawe",
    "Oxenbrigg",
    "Page",
    "Pagge",
    "Palmer",
    "Panshawe",
    "Papley",
    "Parker",
    "Parret",
    "Parris",
    "Parsons",
    "Paston",
    "Pattesley",
    "Payne",
    "Peacok",
    "Pecke",
    "Peckham",
    "Peele",
    "Pekham",
    "Peletoot",
    "Peltie",
    "Pemberton",
    "Pen",
    "Penhallick",
    "Pennebrygg",
    "Perchehay",
    "Perot",
    "Perryvalle",
    "Petham",
    "Petley",
    "Pettit",
    "Pettwoode",
    "Peyton",
    "Phelip",
    "Philips",
    "Playters",
    "Plessi",
    "Plymmyswoode",
    "Poffe",
    "Pole",
    "Polsted",
    "Polton",
    "Porter",
    "Portyngton",
    "Potter",
    "Poulet",
    "Pownder",
    "Pratt",
    "Pray",
    "Prelatte",
    "Prophete",
    "Prowd",
    "Purlles",
    "Pursglove",
    "Purvoche",
    "Pygott",
    "Pylet",
    "Pynnoke",
    "Pynty",
    "Quintin",
    "Radley",
    "Rampston",
    "Ramsey",
    "Ratcliff",
    "Rawlyn",
    "Rawson",
    "Raynsford",
    "Rede",
    "Redman",
    "Reeve",
    "Reynes",
    "Reynesford",
    "Richeman",
    "Rikhill",
    "Risley",
    "Roberts",
    "Robertson",
    "Robins",
    "Robynson",
    "Rochester",
    "Rochforth",
    "Roland",
    "Rolleston",
    "Rondel",
    "Ront",
    "Roper",
    "Rotheley",
    "Rous",
    "Rowdon",
    "Rowe",
    "Rowlatt",
    "Rowley",
    "Rudhall",
    "Rufford",
    "Ruggenale",
    "Ruggeweyn",
    "Rusche",
    "Russell",
    "Ryall",
    "Rykeworth",
    "Rynger",
    "Ryppringham",
    "Sacheverell",
    "Sackville",
    "Sadler",
    "Salford",
    "Salle",
    "Salter",
    "Saltonstall",
    "Sampson",
    "Samuell",
    "Sanburne",
    "Sandes",
    "Saunders",
    "Saunterton",
    "Savill",
    "Sayer",
    "Saynsbery",
    "Scarclyf",
    "Scollfyld",
    "Scot",
    "Scrogs",
    "Scrope",
    "Sedley",
    "Sedlow",
    "Seger",
    "Selwyn",
    "Sencler",
    "Sentjohn",
    "Serche",
    "Sever",
    "Seymour",
    "Seyntaubyn",
    "Seys",
    "Sharman",
    "Shawe",
    "Sheffeld",
    "Sheraton",
    "Sherbourne",
    "Sherman",
    "Shevington",
    "Shingleton",
    "Shipwash",
    "Shiveley",
    "Shorditch",
    "Shosmyth",
    "Shotbolt",
    "Shylton",
    "Sibill",
    "Silvester",
    "Skipwith",
    "Sleford",
    "Slyfield",
    "Smith",
    "Snayth",
    "Snell",
    "Snelling",
    "Sotton",
    "Sparrow",
    "Spebynton",
    "Speir",
    "Spelman",
    "Spencer",
    "Spetyll",
    "Spicer",
    "Sprottle",
    "Sprunt",
    "Stace",
    "Stanbury",
    "Standon",
    "Stanley",
    "Stanwix",
    "Staple",
    "Staunton",
    "Staverton",
    "Stepney",
    "Stevyn",
    "Stocks",
    "Stodeley",
    "Stoke",
    "Stokerton",
    "Stokes",
    "Stokey",
    "Stokton",
    "Stone",
    "Stoner",
    "Stoughton",
    "Strachleigh",
    "Strader",
    "Strangewayes",
    "Strelley",
    "Strete",
    "Stubbe",
    "Styles",
    "Stylle",
    "Styward",
    "Sulyard",
    "Sumner",
    "Swan",
    "Swetecok",
    "Swetenham",
    "Switte",
    "Symeon",
    "Symons",
    "Tabard",
    "Tame",
    "Taylor",
    "Tedcastle",
    "Theobauld",
    "Thomas",
    "Thornburgh",
    "Thorne",
    "Thornton",
    "Thorp",
    "Throkmorton",
    "Thursby",
    "Tibborde",
    "Tilghman",
    "Tiploft",
    "Topsfield",
    "Torryngton",
    "Tothyll",
    "Town",
    "Tregonwell",
    "Treningham",
    "Trenowyth",
    "Trevet",
    "Trumpington",
    "Tubney",
    "Turner",
    "Twarby",
    "Tweedye",
    "Tyndall",
    "Tyrell",
    "Ufford",
    "Underhill",
    "Unton",
    "Upton",
    "Urswic",
    "Vass",
    "Vaughan",
    "Vawdrey",
    "Veldon",
    "Verney",
    "Vernon",
    "Vinter",
    "Wade",
    "Wadham",
    "Wake",
    "Waldegrave",
    "Waldeley",
    "Walden",
    "Walford",
    "Walkden",
    "Walker",
    "Wallace",
    "Walley",
    "Walrond",
    "Walsch",
    "Waltham",
    "Walton",
    "Wanteley",
    "Wappelode",
    "Warbulton",
    "Warde",
    "Wardeby",
    "Wardrieu",
    "Wardyworth",
    "Warner",
    "Warren",
    "Wayte",
    "Webb",
    "Weekes",
    "Welbek",
    "Welby",
    "Wellins",
    "Wenman",
    "Wensley",
    "West",
    "Westbrook",
    "Westlake",
    "Weston",
    "Wetherden",
    "Wexcombe",
    "Whalley",
    "White",
    "Whitewood",
    "Whowood",
    "Whytton",
    "Whytyng",
    "Wightman",
    "Wilkins",
    "Williams",
    "Willys",
    "Wilson",
    "Windham",
    "Wingfield",
    "Wiseman",
    "Woode",
    "Worsley",
    "Wotton",
    "Wright",
    "Wyard",
    "Wyatt",
    "Wyghtham",
    "Wylde",
    "Wymer",
    "Wyncall",
    "Wynston",
    "Wynstryngham",
    "Wynter",
    "Wythinghall",
    "Yate",
    "Yerde",
    "York",
    "Young"
  ],
  "useMiddleName": true
}
